[{"token_name":"TOKENH01","token_sellable":"no vendible","token_price":"-","token_state":"Eliminado","token_ler":"0103","participant_name":"Tecnun","location":[-1.9895696421108424,43.303752636703265],"timestamp":1607093051},{"token_name":"TOKENH02|","token_sellable":"no vendible","token_price":"-","token_state":"Eliminado","token_ler":"0103","participant_name":"Tecnun","location":[-2.051604228938711,43.257372349121724],"timestamp":1616052074},{"token_name":"TOKENH03","token_sellable":"no vendible","token_price":"-","token_state":"Eliminado","token_ler":"010102","participant_name":"Tecnun","location":[-2.051604228938711,43.257372349121724],"timestamp":1616052398},{"token_name":"TOKENH04","token_sellable":"no vendible","token_price":"-","token_state":"Eliminado","token_ler":"0103","participant_name":"Tecnun","location":[-2.078608638766531,43.23336415668372],"timestamp":1616055687},{"token_name":"TOKENH05","token_sellable":"no vendible","token_price":"-","token_state":"Eliminado","token_ler":"010307*","participant_name":"Tecnun","location":[-2.078608638766531,43.23336415668372],"timestamp":1616055938}]